LICENSE.md
log4j_detector_to_csv/__init__.py
log4j_detector_to_csv/main.py
log4j_detector_to_csv-0.1.7.dist-info/entry_points.txt
log4j_detector_to_csv-0.1.7.dist-info/LICENSE.md
log4j_detector_to_csv-0.1.7.dist-info/WHEEL
log4j_detector_to_csv-0.1.7.dist-info/METADATA
log4j_detector_to_csv-0.1.7.dist-info/RECORD
